dccpu/__init__.py
dccpu/generators.py
dccpu-0.3.7.dist-info/DESCRIPTION.rst
dccpu-0.3.7.dist-info/METADATA
dccpu-0.3.7.dist-info/RECORD
dccpu-0.3.7.dist-info/WHEEL
dccpu-0.3.7.dist-info/metadata.json
dccpu-0.3.7.dist-info/top_level.txt
